crpred/__init__.py
crpred/advanced_models/__init__.py
crpred/advanced_models/agent.py
crpred/advanced_models/agent_predictor.py
crpred/advanced_models/idm_agent.py
crpred/advanced_models/idm_predictor.py
crpred/advanced_models/mobil_agent.py
crpred/advanced_models/mobil_predictor.py
crpred/advanced_models/utility/__init__.py
crpred/advanced_models/utility/lanelets.py
crpred/basic_models/__init__.py
crpred/basic_models/constant_acceleration_predictor.py
crpred/basic_models/constant_velocity_predictor.py
crpred/basic_models/motion_model_predictor.py
crpred/ground_truth_predictor.py
crpred/predictor_factory.py
crpred/predictor_interface.py
crpred/utility/__init__.py
crpred/utility/common.py
crpred/utility/config.py
crpred/utility/visualization.py
commonroad_prediction-0.1.1.dist-info/LICENSE.txt
commonroad_prediction-0.1.1.dist-info/METADATA
commonroad_prediction-0.1.1.dist-info/WHEEL
commonroad_prediction-0.1.1.dist-info/RECORD
