Metadata-Version: 2.1
Name: commonroad-prediction
Version: 0.1.1
Summary: A collection and interface for CommonRoad prediction algorithms.
Home-page: https://commonroad.in.tum.de
License: BSD-3-Clause
Keywords: autonomous,automated,vehicles,driving,motion,planning,prediction
Author: Cyber-Physical Systems Group, Technical University of Munich
Author-email: commonroad@lists.lrz.de
Requires-Python: >=3.9,<3.12
Classifier: License :: OSI Approved :: BSD License
Classifier: Operating System :: POSIX :: Linux
Classifier: Programming Language :: Python :: 3
Classifier: Programming Language :: Python :: 3.9
Classifier: Programming Language :: Python :: 3.10
Classifier: Programming Language :: Python :: 3.11
Requires-Dist: commonroad-drivability-checker (>=2024.1)
Requires-Dist: commonroad-io (>=2024.1)
Requires-Dist: imageio (>=2.31.1,<3.0.0)
Requires-Dist: numpy (<2.0)
